easytgbot/__init__.py
easytgbot/admin.py
easytgbot/app.py
easytgbot/cli.py
easytgbot/decorators.py
easytgbot/file_handler.py
easytgbot/mylogging.py
easytgbot/send.py
easytgbot/settings.py
easytgbot/text_handler.py
easytgbot/utils/templates/.env
easytgbot/utils/templates/main.py
easytgbot/utils/templates/text.xlsx
easytgbot/utils/utils.py
easytgbot/validate_text_file.py
easytgbot-0.1.2.dist-info/entry_points.txt
easytgbot-0.1.2.dist-info/LICENSE
easytgbot-0.1.2.dist-info/METADATA
easytgbot-0.1.2.dist-info/WHEEL
easytgbot-0.1.2.dist-info/RECORD
